etcd/__init__.py
etcd/auth.py
etcd/client.py
etcd/lock.py
etcd/tests/__init__.py
etcd/tests/test_auth.py
etcd/tests/integration/__init__.py
etcd/tests/integration/helpers.py
etcd/tests/integration/test_simple.py
etcd/tests/integration/test_ssl.py
etcd/tests/unit/__init__.py
etcd/tests/unit/test_client.py
etcd/tests/unit/test_lock.py
etcd/tests/unit/test_old_request.py
etcd/tests/unit/test_request.py
etcd/tests/unit/test_result.py
romana_python_etcd-0.1.1.dist-info/DESCRIPTION.rst
romana_python_etcd-0.1.1.dist-info/METADATA
romana_python_etcd-0.1.1.dist-info/RECORD
romana_python_etcd-0.1.1.dist-info/WHEEL
romana_python_etcd-0.1.1.dist-info/metadata.json
romana_python_etcd-0.1.1.dist-info/top_level.txt
