Metadata-Version: 2.0
Name: romana-python-etcd
Version: 0.1.1
Summary: A python client for etcd
Home-page: http://github.com/jplana/python-etcd
Author: Jose Plana
Author-email: jplana@gmail.com
License: MIT
Keywords: etcd raft distributed log api client
Platform: UNKNOWN
Classifier: Topic :: System :: Distributed Computing
Classifier: Topic :: Software Development :: Libraries
Classifier: License :: OSI Approved :: MIT License
Classifier: Programming Language :: Python :: 2
Classifier: Programming Language :: Python :: 3
Classifier: Topic :: Database :: Front-Ends
Requires-Dist: dnspython (>=1.13.0)
Requires-Dist: urllib3 (>=1.7.1)
